MVVsBahn/MVVsBahn.py
MVVsBahn/__init__.py
MVVsBahn-0.0.1.dist-info/METADATA
MVVsBahn-0.0.1.dist-info/WHEEL
MVVsBahn-0.0.1.dist-info/top_level.txt
MVVsBahn-0.0.1.dist-info/RECORD
